statsflow.py
src/__init__.py
src/statsflow.py
statsflow-0.0.1.dist-info/License
statsflow-0.0.1.dist-info/METADATA
statsflow-0.0.1.dist-info/WHEEL
statsflow-0.0.1.dist-info/top_level.txt
statsflow-0.0.1.dist-info/RECORD
