Metadata-Version: 2.1
Name: statsflow
Version: 0.0.1
Summary: This Python package consist of various statistical modules and function that can be  very useful for data preprocessing,data transformation,EDA and seamlessly improves the performance of Ml-Pipeline
Home-page: https://github.com/ragulslrk/statsflow_pkgs
Author: Ragul s
License: UNKNOWN
Keywords: statistics,plotting,probplot,data transformation
Platform: UNKNOWN
Classifier: Programming Language :: Python :: 3
Classifier: License :: OSI Approved :: MIT License
Classifier: Operating System :: OS Independent
Requires-Python: >=3.9
License-File: License
Requires-Dist: numpy
Requires-Dist: pandas
Requires-Dist: matplotlib
Requires-Dist: scipy
